{
  "meta": {
    "version": "1.0",
    "generated": "2026-04-24",
    "description": "SNS 投稿パイプラインの状態ファイル。sns-draft.mjs が 在庫_マップ.md から読み込んだ候補の posted/draft 状態を管理。",
    "vaultPath": "../lecsy/_Vault",
    "inventoryPath": "../lecsy/_Vault/SNS/在庫_マップ.md",
    "draftsDir": "../lecsy/_Vault/SNS/ドラフト",
    "archiveDir": "../lecsy/_Vault/SNS/公開済",
    "defaultDraftsPerDay": 3
  },
  "posts": [
    {
      "id": "AI-ebab479a",
      "ch": "X",
      "status": "blocked",
      "reasons": [
        "length 282 > 280"
      ],
      "generatedAt": "2026-04-24T21:08:48.791Z",
      "blockedAt": "2026-04-24T21:08:48.989Z"
    },
    {
      "id": "AI-ebab479a",
      "ch": "X",
      "status": "blocked",
      "reasons": [
        "NG keyword: \"AI-powered\""
      ],
      "generatedAt": "2026-04-24T21:09:08.338Z",
      "blockedAt": "2026-04-24T21:09:08.596Z"
    },
    {
      "id": "AI-ebab479a",
      "ch": "X",
      "lang": "ja",
      "status": "dry-run",
      "tweetId": null,
      "url": null,
      "postedAt": "2026-04-24T21:09:32.603Z",
      "generatedAt": "2026-04-24T21:09:32.599Z"
    },
    {
      "id": "AI-85c88209",
      "ch": "X",
      "lang": "ja",
      "status": "dry-run",
      "tweetId": null,
      "url": null,
      "postedAt": "2026-04-24T21:16:43.206Z",
      "generatedAt": "2026-04-24T21:16:43.204Z"
    },
    {
      "id": "AI-85c88209",
      "ch": "X",
      "status": "blocked",
      "reasons": [
        "length 310 > 280"
      ],
      "generatedAt": "2026-04-24T21:17:00.973Z",
      "blockedAt": "2026-04-24T21:17:01.179Z"
    },
    {
      "id": "AI-85c88209",
      "ch": "X",
      "status": "blocked",
      "reasons": [
        "length 323 > 280"
      ],
      "generatedAt": "2026-04-24T21:17:32.316Z",
      "blockedAt": "2026-04-24T21:17:32.568Z"
    },
    {
      "id": "AI-85c88209",
      "ch": "X",
      "status": "blocked",
      "reasons": [
        "length 307 > 280"
      ],
      "generatedAt": "2026-04-24T21:18:03.368Z",
      "blockedAt": "2026-04-24T21:18:03.775Z"
    },
    {
      "id": "AI-85c88209",
      "ch": "X",
      "status": "error",
      "error": "Request failed with code 403",
      "erroredAt": "2026-04-24T21:18:43.324Z"
    },
    {
      "id": "AI-85c88209",
      "ch": "X",
      "status": "blocked",
      "reasons": [
        "length 313 (X-weighted) > 280"
      ],
      "generatedAt": "2026-04-24T21:19:40.957Z",
      "blockedAt": "2026-04-24T21:19:41.136Z"
    },
    {
      "id": "AI-85c88209",
      "ch": "X",
      "lang": "ja",
      "status": "posted",
      "tweetId": "2047787722459296236",
      "url": "https://x.com/Ww83vjNwSLXhV6B/status/2047787722459296236",
      "postedAt": "2026-04-24T21:20:13.906Z",
      "generatedAt": "2026-04-24T21:20:13.389Z"
    },
    {
      "id": "AI-f785155d",
      "ch": "X",
      "lang": "ja",
      "status": "dry-run",
      "tweetId": null,
      "url": null,
      "postedAt": "2026-04-25T15:48:44.646Z",
      "generatedAt": "2026-04-25T15:48:44.644Z"
    },
    {
      "id": "AI-f785155d",
      "ch": "X",
      "lang": "ja",
      "status": "dry-run",
      "tweetId": null,
      "url": null,
      "postedAt": "2026-04-25T15:56:19.073Z",
      "generatedAt": "2026-04-25T15:56:19.070Z"
    },
    {
      "id": "AI-f785155d",
      "ch": "X",
      "lang": "ja",
      "status": "dry-run",
      "tweetId": null,
      "url": null,
      "postedAt": "2026-04-25T15:56:21.878Z",
      "generatedAt": "2026-04-25T15:56:21.876Z"
    },
    {
      "id": "AI-f785155d",
      "ch": "X",
      "lang": "ja",
      "status": "dry-run",
      "tweetId": null,
      "url": null,
      "postedAt": "2026-04-25T15:56:27.567Z",
      "generatedAt": "2026-04-25T15:56:27.563Z"
    },
    {
      "id": "AI-f785155d",
      "ch": "X",
      "lang": "ja",
      "status": "dry-run",
      "tweetId": null,
      "url": null,
      "postedAt": "2026-04-25T15:56:37.642Z",
      "generatedAt": "2026-04-25T15:56:37.640Z"
    },
    {
      "id": "AI-6a4b53c5",
      "ch": "X",
      "lang": "ja",
      "status": "dry-run",
      "tweetId": null,
      "url": null,
      "postedAt": "2026-04-25T15:56:40.401Z",
      "generatedAt": "2026-04-25T15:56:40.398Z"
    },
    {
      "id": "AI-c62ed384",
      "ch": "X",
      "lang": "ja",
      "status": "dry-run",
      "tweetId": null,
      "url": null,
      "postedAt": "2026-04-25T15:56:43.277Z",
      "generatedAt": "2026-04-25T15:56:43.274Z"
    },
    {
      "id": "AI-f785155d",
      "ch": "X",
      "lang": "ja",
      "status": "dry-run",
      "tweetId": null,
      "url": null,
      "postedAt": "2026-04-25T15:58:54.930Z",
      "generatedAt": "2026-04-25T15:58:54.928Z"
    },
    {
      "id": "AI-f785155d",
      "ch": "X",
      "lang": "ja",
      "status": "posted",
      "tweetId": "2048184824922550405",
      "url": "https://x.com/Ww83vjNwSLXhV6B/status/2048184824922550405",
      "postedAt": "2026-04-25T23:38:10.485Z",
      "generatedAt": "2026-04-25T23:38:10.280Z"
    },
    {
      "id": "SNS-501",
      "ch": "X",
      "status": "error",
      "error": "no source content for SNS-501",
      "erroredAt": "2026-04-26T05:54:54.385Z"
    },
    {
      "id": "SNS-502",
      "ch": "X",
      "status": "error",
      "error": "no source content for SNS-502",
      "erroredAt": "2026-04-26T05:54:54.448Z"
    },
    {
      "id": "SNS-503",
      "ch": "X",
      "status": "error",
      "error": "no source content for SNS-503",
      "erroredAt": "2026-04-26T05:54:54.499Z"
    },
    {
      "id": "AI-6a4b53c5",
      "ch": "X",
      "lang": "ja",
      "status": "posted",
      "tweetId": "2048279645351469404",
      "url": "https://x.com/Ww83vjNwSLXhV6B/status/2048279645351469404",
      "postedAt": "2026-04-26T05:54:57.381Z",
      "generatedAt": "2026-04-26T05:54:57.209Z"
    },
    {
      "id": "AI-c62ed384",
      "ch": "X",
      "lang": "ja",
      "status": "posted",
      "tweetId": "2048381078948204625",
      "url": "https://x.com/Ww83vjNwSLXhV6B/status/2048381078948204625",
      "postedAt": "2026-04-26T12:38:01.076Z",
      "generatedAt": "2026-04-26T12:38:00.849Z"
    },
    {
      "id": "SNS-501",
      "ch": "X",
      "status": "error",
      "error": "no source content for SNS-501",
      "erroredAt": "2026-04-26T23:39:08.064Z"
    },
    {
      "id": "SNS-502",
      "ch": "X",
      "status": "error",
      "error": "no source content for SNS-502",
      "erroredAt": "2026-04-26T23:39:08.196Z"
    },
    {
      "id": "SNS-503",
      "ch": "X",
      "status": "error",
      "error": "no source content for SNS-503",
      "erroredAt": "2026-04-26T23:39:08.274Z"
    },
    {
      "id": "SNS-501",
      "ch": "X",
      "status": "error",
      "error": "no source content for SNS-501",
      "erroredAt": "2026-04-27T06:13:36.677Z"
    },
    {
      "id": "SNS-502",
      "ch": "X",
      "status": "error",
      "error": "no source content for SNS-502",
      "erroredAt": "2026-04-27T06:13:36.963Z"
    },
    {
      "id": "SNS-503",
      "ch": "X",
      "status": "error",
      "error": "no source content for SNS-503",
      "erroredAt": "2026-04-27T06:13:37.270Z"
    },
    {
      "id": "SNS-501",
      "ch": "X",
      "status": "error",
      "error": "no source content for SNS-501",
      "erroredAt": "2026-04-27T13:13:53.129Z"
    },
    {
      "id": "SNS-502",
      "ch": "X",
      "status": "error",
      "error": "no source content for SNS-502",
      "erroredAt": "2026-04-27T13:13:53.232Z"
    },
    {
      "id": "SNS-503",
      "ch": "X",
      "status": "error",
      "error": "no source content for SNS-503",
      "erroredAt": "2026-04-27T13:13:53.304Z"
    },
    {
      "id": "AI-152cb1f3",
      "ch": "X",
      "lang": "ja",
      "status": "posted",
      "tweetId": "2048759030311526714",
      "url": "https://x.com/Ww83vjNwSLXhV6B/status/2048759030311526714",
      "postedAt": "2026-04-27T13:39:51.722Z",
      "generatedAt": "2026-04-27T13:39:51.407Z"
    }
  ]
}
